{"is_source_file": true, "format": "JavaScript", "description": "The provided file is a React application's main component (App.js), implementing the root layout, theme toggling, API data loading, note selection, editing, saving, deleting, and routing.", "external_files": ["./App.css", "./styles/theme.css", "./components/Layout/Header", "./components/Layout/Sidebar", "./components/Notes", "./api/notesApi", "./context/NotesContext", "./routes/AppRouter", "./components/Common"], "external_methods": ["notesApi.listNotes", "notesApi.updateNote", "notesApi.deleteNote"], "published": ["App"], "classes": [], "methods": [{"name": "AppInner()", "description": "Main application component that manages note list state, theme, routing, and user interactions like editing, saving, and deleting notes.", "scope": "", "scopeKind": ""}, {"name": "App()", "description": "Wrapper component that provides routing context around the main AppInner component.", "scope": "", "scopeKind": ""}, {"name": "handleKeyDown(e)", "scope": "AppInner", "scopeKind": "function", "description": "unavailable"}], "calls": ["document.documentElement.setAttribute", "notesApi.listNotes", "actions.setLoading", "actions.initLoad", "actions.setError", "actions.updateNote", "actions.deleteNote", "navigate", "window.confirm", "notesApi.updateNote", "notesApi.deleteNote", "setTimeout", "window.addEventListener", "window.removeEventListener", "setTheme", "useMemo", "useCallback"], "search-terms": ["React", "useNotesContext", "NotesApi", "note editing", "note saving", "note deletion", "routing", "theme toggle", "keyboard shortcuts", "error handling", "initial data load"], "state": 2, "file_id": 9, "knowledge_revision": 107, "git_revision": "f876ddf5444e827418ea22995b40ee52e3b6f352", "revision_history": [{"24": "e6255435e28978367549c30d36db421f58e6e130"}, {"42": "e6255435e28978367549c30d36db421f58e6e130"}, {"87": "1f507dc7110b3968edabd656632dff415391b487"}, {"93": "24e97b9ad063280d19717be26bc351f82affd3ea"}, {"107": "f876ddf5444e827418ea22995b40ee52e3b6f352"}], "ctags": [{"_type": "tag", "name": "14", "path": "/home/kavia/workspace/code-generation/note-keeper-29152-29197/notes_frontend/src/App.js", "pattern": "/^            {state.loading ? <Spinner size={14} \\/> : null}$/", "language": "JavaScript", "kind": "field", "scope": "state.loading", "scopeKind": "class"}, {"_type": "tag", "name": "App", "path": "/home/kavia/workspace/code-generation/note-keeper-29152-29197/notes_frontend/src/App.js", "pattern": "/^function App() {$/", "language": "JavaScript", "kind": "function", "signature": "()"}, {"_type": "tag", "name": "AppInner", "path": "/home/kavia/workspace/code-generation/note-keeper-29152-29197/notes_frontend/src/App.js", "pattern": "/^function AppInner() {$/", "language": "JavaScript", "kind": "function", "signature": "()"}, {"_type": "tag", "name": "app-shell ocean-gradient", "path": "/home/kavia/workspace/code-generation/note-keeper-29152-29197/notes_frontend/src/App.js", "pattern": "/^    <div className={`app-shell ocean-gradient`}>$/", "language": "JavaScript", "kind": "field", "scope": "AppInner.AnonymousClasse07c0fd90101", "scopeKind": "class"}, {"_type": "tag", "name": "handleKeyDown", "path": "/home/kavia/workspace/code-generation/note-keeper-29152-29197/notes_frontend/src/App.js", "pattern": "/^    function handleKeyDown(e) {$/", "language": "JavaScript", "kind": "function", "signature": "(e)", "scope": "AppInner", "scopeKind": "function"}, {"_type": "tag", "name": "handleSelectNote", "path": "/home/kavia/workspace/code-generation/note-keeper-29152-29197/notes_frontend/src/App.js", "pattern": "/^                onSelect={handleSelectNote}$/", "language": "JavaScript", "kind": "field", "scope": "AppInner.onSelect", "scopeKind": "class"}, {"_type": "tag", "name": "notesArray", "path": "/home/kavia/workspace/code-generation/note-keeper-29152-29197/notes_frontend/src/App.js", "pattern": "/^                notes={notesArray}$/", "language": "JavaScript", "kind": "field", "scope": "AppInner.notes", "scopeKind": "class"}, {"_type": "tag", "name": "selectedId", "path": "/home/kavia/workspace/code-generation/note-keeper-29152-29197/notes_frontend/src/App.js", "pattern": "/^                selectedId={selectedId}$/", "language": "JavaScript", "kind": "field", "scope": "AppInner.selectedId", "scopeKind": "class"}, {"_type": "tag", "name": "state", "path": "/home/kavia/workspace/code-generation/note-keeper-29152-29197/notes_frontend/src/App.js", "pattern": "/^                searchQuery={state.query}$/", "language": "JavaScript", "kind": "field", "scope": "AppInner.searchQuery", "scopeKind": "class"}, {"_type": "tag", "name": "state", "path": "/home/kavia/workspace/code-generation/note-keeper-29152-29197/notes_frontend/src/App.js", "pattern": "/^          aria-busy={state.loading ? 'true' : 'false'}$/", "language": "JavaScript", "kind": "field", "scope": "AppInner.aria", "scopeKind": "class"}, {"_type": "tag", "name": "true", "path": "/home/kavia/workspace/code-generation/note-keeper-29152-29197/notes_frontend/src/App.js", "pattern": "/^                searchable={true}$/", "language": "JavaScript", "kind": "field", "scope": "AppInner.searchable", "scopeKind": "class"}], "hash": "3337e3239573a8ca013a590456e14d96", "format-version": 4, "code-base-name": "notes_frontend", "filename": "notes_frontend/src/App.js", "fields": [{"name": "{state.loading ? <Spinner size={14} \\/> : null}", "scope": "state.loading", "scopeKind": "class", "description": "unavailable"}, {"name": "<div className={`app-shell ocean-gradient`}>", "scope": "AppInner.AnonymousClasse07c0fd90101", "scopeKind": "class", "description": "unavailable"}, {"name": "onSelect={handleSelectNote}", "scope": "AppInner.onSelect", "scopeKind": "class", "description": "unavailable"}, {"name": "notes={notesArray}", "scope": "AppInner.notes", "scopeKind": "class", "description": "unavailable"}, {"name": "selectedId={selectedId}", "scope": "AppInner.selectedId", "scopeKind": "class", "description": "unavailable"}, {"name": "searchQuery={state.query}", "scope": "AppInner.searchQuery", "scopeKind": "class", "description": "unavailable"}, {"name": "aria-busy={state.loading ? 'true' : 'false'}", "scope": "AppInner.aria", "scopeKind": "class", "description": "unavailable"}, {"name": "searchable={true}", "scope": "AppInner.searchable", "scopeKind": "class", "description": "unavailable"}]}